Cargo.lock
Cargo.toml
MANIFEST.in
README.rst
build.rs
pyproject.toml
setup.py
darknetpy/__init__.py
darknetpy.egg-info/PKG-INFO
darknetpy.egg-info/SOURCES.txt
darknetpy.egg-info/dependency_links.txt
darknetpy.egg-info/not-zip-safe
darknetpy.egg-info/top_level.txt
darknetpy/detector/__init__.py
src/lib.rs