Metadata-Version: 1.1
Name: darknetpy
Version: 4.2
Summary: UNKNOWN
Home-page: https://github.com/danielgatis/darknetpy
Author: Daniel Gatis Carrazzoni
Author-email: danielgatis@gmail.com
License: BSD License
Platform: Linux
Classifier: Intended Audience :: Developers
Classifier: Programming Language :: Python
Classifier: Programming Language :: Python :: 3
Classifier: Operating System :: POSIX :: Linux
